xphyle/__init__.py
xphyle/formats.py
xphyle/paths.py
xphyle/progress.py
xphyle/types.py
xphyle/urls.py
xphyle/utils.py
xphyle-4.4.4.dist-info/LICENSE
xphyle-4.4.4.dist-info/METADATA
xphyle-4.4.4.dist-info/WHEEL
xphyle-4.4.4.dist-info/top_level.txt
xphyle-4.4.4.dist-info/RECORD
