Metadata-Version: 2.1
Name: xphyle
Version: 4.4.4
Summary: Utilities for working with files.
Home-page: https://github.com/jdidion/xphyle
Author: John Didion
Author-email: github@didion.net
License: MIT
Classifier: Development Status :: 5 - Production/Stable
Classifier: Intended Audience :: Developers
Classifier: Topic :: Software Development :: Libraries :: Python Modules
Classifier: License :: OSI Approved :: MIT License
Classifier: License :: Public Domain
Classifier: Programming Language :: Python :: 3 :: Only
Classifier: Programming Language :: Python :: 3.6
Classifier: Programming Language :: Python :: 3.7
Classifier: Programming Language :: Python :: 3.8
License-File: LICENSE
Requires-Dist: pokrok
Provides-Extra: performance
Requires-Dist: lorem ; extra == 'performance'
Provides-Extra: zstd
Requires-Dist: zstandard ; extra == 'zstd'
